{
  "updatedWords": [
    {
      "id": "duo_648",
      "japanese": "ポスター",
      "english": "poster",
      "type": "noun",
      "exampleSentences": [
        {
          "japanese": "このポスターはかっこいいです。",
          "english": "This poster is cool.",
          "context": "statement",
          "level": "1-1",
          "isAIGenerated": true
        },
        {
          "japanese": "へやにえいがのポスターをはりました。",
          "english": "I put up a movie poster in my room.",
          "context": "statement",
          "level": "2-1",
          "isAIGenerated": true
        },
        {
          "japanese": "むすこはアニメがだいすきですから、へやにたくさんポスターがあります。",
          "english": "My son loves anime, so there are many posters in his room.",
          "context": "statement",
          "level": "3-1",
          "isAIGenerated": true
        }
      ]
    },
    {
      "id": "duo_647",
      "japanese": "はいゆう",
      "english": "actor",
      "type": "noun",
      "exampleSentences": [
        {
          "japanese": "あのはいゆうはゆうめいです。",
          "english": "That actor is famous.",
          "context": "statement",
          "level": "1-1",
          "isAIGenerated": true
        },
        {
          "japanese": "このえいがのはいゆうはだれですか。",
          "english": "Who is the actor in this movie?",
          "context": "question",
          "level": "2-1",
          "isAIGenerated": true
        },
        {
          "japanese": "私のすきなはいゆうは日本のドラマによくでますから、まいしゅう見ています。",
          "english": "My favorite actor often appears in Japanese dramas, so I watch them every week.",
          "context": "statement",
          "level": "3-1",
          "isAIGenerated": true
        }
      ]
    },
    {
      "id": "duo_646",
      "japanese": "見ません",
      "english": "does not see, do not watch, does not look at",
      "type": "verb",
      "exampleSentences": [
        {
          "japanese": "テレビを見ません。",
          "english": "I don't watch TV.",
          "context": "statement",
          "level": "1-1",
          "isAIGenerated": true
        },
        {
          "japanese": "私はホラーえいがを見ません。",
          "english": "I don't watch horror movies.",
          "context": "statement",
          "level": "2-1",
          "isAIGenerated": true
        },
        {
          "japanese": "父はいそがしいですから、テレビをあまり見ませんが、ニュースだけは見ます。",
          "english": "My father is busy, so he doesn't watch much TV, but he only watches the news.",
          "context": "statement",
          "level": "3-1",
          "isAIGenerated": true
        }
      ]
    },
    {
      "id": "duo_645",
      "japanese": "カードゲーム",
      "english": "card game",
      "type": "noun",
      "exampleSentences": [
        {
          "japanese": "カードゲームがすきです。",
          "english": "I like card games.",
          "context": "statement",
          "level": "1-1",
          "isAIGenerated": true
        },
        {
          "japanese": "しゅうまつ、かぞくとカードゲームをしませんか。",
          "english": "Would you like to play card games with the family this weekend?",
          "context": "question",
          "level": "2-1",
          "isAIGenerated": true
        },
        {
          "japanese": "雨の日はそとにでかけませんから、こどもといっしょにカードゲームをたのしみます。",
          "english": "On rainy days, we don't go outside, so I enjoy card games with the children.",
          "context": "statement",
          "level": "3-1",
          "isAIGenerated": true
        }
      ]
    },
    {
      "id": "duo_643",
      "japanese": "しません",
      "english": "do not, will not, does not",
      "type": "verb",
      "exampleSentences": [
        {
          "japanese": "今日はうんどうしません。",
          "english": "I won't exercise today.",
          "context": "statement",
          "level": "1-1",
          "isAIGenerated": true
        },
        {
          "japanese": "日曜日はしごとをしません。",
          "english": "I don't work on Sundays.",
          "context": "statement",
          "level": "2-1",
          "isAIGenerated": true
        },
        {
          "japanese": "つかれていますから、今日はそうじもせんたくもしません。",
          "english": "I'm tired, so I won't do cleaning or laundry today.",
          "context": "statement",
          "level": "3-1",
          "isAIGenerated": true
        }
      ]
    },
    {
      "id": "duo_642",
      "japanese": "パズル",
      "english": "puzzle",
      "type": "noun",
      "exampleSentences": [
        {
          "japanese": "パズルがすきです。",
          "english": "I like puzzles.",
          "context": "statement",
          "level": "1-1",
          "isAIGenerated": true
        },
        {
          "japanese": "このパズルはむずかしいですが、おもしろいです。",
          "english": "This puzzle is difficult, but interesting.",
          "context": "statement",
          "level": "2-1",
          "isAIGenerated": true
        },
        {
          "japanese": "おばあさんはまいにちパズルをしますから、あたまがとてもいいです。",
          "english": "My grandmother does puzzles every day, so she's very smart.",
          "context": "statement",
          "level": "3-1",
          "isAIGenerated": true
        }
      ]
    },
    {
      "id": "duo_638",
      "japanese": "ききません",
      "english": "don't really listen to",
      "type": "verb",
      "exampleSentences": [
        {
          "japanese": "ラジオをききません。",
          "english": "I don't listen to the radio.",
          "context": "statement",
          "level": "1-1",
          "isAIGenerated": true
        },
        {
          "japanese": "私はロックをあまりききません。",
          "english": "I don't really listen to rock music.",
          "context": "statement",
          "level": "2-1",
          "isAIGenerated": true
        },
        {
          "japanese": "ジャズはあまりききませんが、Jポップとポップスはよくききます。",
          "english": "I don't really listen to jazz, but I often listen to J-pop and pop music.",
          "context": "statement",
          "level": "3-1",
          "isAIGenerated": true
        }
      ]
    },
    {
      "id": "duo_637",
      "japanese": "ポップス",
      "english": "pop",
      "type": "noun",
      "exampleSentences": [
        {
          "japanese": "ポップスがすきです。",
          "english": "I like pop music.",
          "context": "statement",
          "level": "1-1",
          "isAIGenerated": true
        },
        {
          "japanese": "私はポップスをよくききます。",
          "english": "I often listen to pop music.",
          "context": "statement",
          "level": "2-1",
          "isAIGenerated": true
        },
        {
          "japanese": "むすめはKポップとポップスがだいすきですから、まいにちきいています。",
          "english": "My daughter loves K-pop and pop music, so she listens to them every day.",
          "context": "statement",
          "level": "3-1",
          "isAIGenerated": true
        }
      ]
    },
    {
      "id": "duo_636",
      "japanese": "ノンフィクション",
      "english": "non-fiction",
      "type": "noun",
      "exampleSentences": [
        {
          "japanese": "ノンフィクションを読みます。",
          "english": "I read non-fiction.",
          "context": "statement",
          "level": "1-1",
          "isAIGenerated": true
        },
        {
          "japanese": "私はフィクションよりノンフィクションがすきです。",
          "english": "I like non-fiction more than fiction.",
          "context": "statement",
          "level": "2-1",
          "isAIGenerated": true
        },
        {
          "japanese": "父はれきしのノンフィクションをよく読みますから、本だながいっぱいです。",
          "english": "My father often reads history non-fiction, so his bookshelf is full.",
          "context": "statement",
          "level": "3-1",
          "isAIGenerated": true
        }
      ]
    },
    {
      "id": "duo_632",
      "japanese": "話",
      "english": "talking, conversation, chat",
      "type": "noun",
      "exampleSentences": [
        {
          "japanese": "いい話ですね。",
          "english": "That's a nice story.",
          "context": "statement",
          "level": "1-1",
          "isAIGenerated": true
        },
        {
          "japanese": "ともだちとの話はいつもたのしいです。",
          "english": "Conversations with my friends are always fun.",
          "context": "statement",
          "level": "2-1",
          "isAIGenerated": true
        },
        {
          "japanese": "あにはおもしろい話をたくさん知っていますから、いっしょにいるとたのしいです。",
          "english": "My older brother knows many interesting stories, so it's fun to be with him.",
          "context": "statement",
          "level": "3-1",
          "isAIGenerated": true
        }
      ]
    },
    {
      "id": "duo_628",
      "japanese": "チョコミント",
      "english": "mint chocolate chip",
      "type": "noun",
      "exampleSentences": [
        {
          "japanese": "チョコミントがすきです。",
          "english": "I like mint chocolate chip.",
          "context": "statement",
          "level": "1-1",
          "isAIGenerated": true
        },
        {
          "japanese": "チョコミントのアイスクリームをください。",
          "english": "Mint chocolate chip ice cream, please.",
          "context": "statement",
          "level": "2-1",
          "isAIGenerated": true
        },
        {
          "japanese": "私はチョコミントがだいすきですが、かれしはあまりすきじゃないです。",
          "english": "I love mint chocolate chip, but my boyfriend doesn't really like it.",
          "context": "statement",
          "level": "3-1",
          "isAIGenerated": true
        }
      ]
    },
    {
      "id": "duo_626",
      "japanese": "バニラ",
      "english": "vanilla",
      "type": "noun",
      "exampleSentences": [
        {
          "japanese": "バニラのアイスクリームがすきです。",
          "english": "I like vanilla ice cream.",
          "context": "statement",
          "level": "1-1",
          "isAIGenerated": true
        },
        {
          "japanese": "すきなあじは何ですか。バニラです。",
          "english": "What's your favorite flavor? Vanilla.",
          "context": "answer",
          "level": "2-1",
          "isAIGenerated": true
        },
        {
          "japanese": "こどもはバニラとチョコレートのアイスクリームがだいすきですから、よく買います。",
          "english": "The children love vanilla and chocolate ice cream, so I often buy them.",
          "context": "statement",
          "level": "3-1",
          "isAIGenerated": true
        }
      ]
    },
    {
      "id": "duo_624",
      "japanese": "きいろい",
      "english": "yellow",
      "type": "adjective",
      "exampleSentences": [
        {
          "japanese": "このはなはきいろいです。",
          "english": "This flower is yellow.",
          "context": "statement",
          "level": "1-1",
          "isAIGenerated": true
        },
        {
          "japanese": "むすめはきいろいドレスがほしいです。",
          "english": "My daughter wants a yellow dress.",
          "context": "statement",
          "level": "2-1",
          "isAIGenerated": true
        },
        {
          "japanese": "はるになると、にわにきいろいはながたくさんさきますから、とてもきれいです。",
          "english": "When spring comes, many yellow flowers bloom in the garden, so it's very beautiful.",
          "context": "statement",
          "level": "3-1",
          "isAIGenerated": true
        }
      ]
    },
    {
      "id": "duo_623",
      "japanese": "ショー",
      "english": "show",
      "type": "noun",
      "exampleSentences": [
        {
          "japanese": "ショーを見ます。",
          "english": "I'll watch the show.",
          "context": "statement",
          "level": "1-1",
          "isAIGenerated": true
        },
        {
          "japanese": "ゆうえんちでショーを見ませんか。",
          "english": "Would you like to watch a show at the theme park?",
          "context": "question",
          "level": "2-1",
          "isAIGenerated": true
        },
        {
          "japanese": "このゆうえんちのショーはとてもにんきですから、はやく行きましょう。",
          "english": "The show at this theme park is very popular, so let's go early.",
          "context": "statement",
          "level": "3-1",
          "isAIGenerated": true
        }
      ]
    },
    {
      "id": "duo_621",
      "japanese": "見ましょうか",
      "english": "should we see",
      "type": "verb",
      "exampleSentences": [
        {
          "japanese": "えいがを見ましょうか。",
          "english": "Should we watch a movie?",
          "context": "question",
          "level": "1-1",
          "isAIGenerated": true
        },
        {
          "japanese": "今夜、いっしょにテレビを見ましょうか。",
          "english": "Should we watch TV together tonight?",
          "context": "question",
          "level": "2-1",
          "isAIGenerated": true
        },
        {
          "japanese": "雨ですから、うちでえいがを見ましょうか。ポップコーンも買いましょう。",
          "english": "It's raining, so should we watch a movie at home? Let's also buy popcorn.",
          "context": "question",
          "level": "3-1",
          "isAIGenerated": true
        }
      ]
    },
    {
      "id": "duo_620",
      "japanese": "ゴーカート",
      "english": "go-kart",
      "type": "noun",
      "exampleSentences": [
        {
          "japanese": "ゴーカートにのりたいです。",
          "english": "I want to ride a go-kart.",
          "context": "statement",
          "level": "1-1",
          "isAIGenerated": true
        },
        {
          "japanese": "ゆうえんちでゴーカートにのりませんか。",
          "english": "Would you like to ride go-karts at the theme park?",
          "context": "question",
          "level": "2-1",
          "isAIGenerated": true
        },
        {
          "japanese": "むすこはゴーカートがだいすきですから、ゆうえんちに行くといつものります。",
          "english": "My son loves go-karts, so he always rides them when we go to the theme park.",
          "context": "statement",
          "level": "3-1",
          "isAIGenerated": true
        }
      ]
    },
    {
      "id": "duo_618",
      "japanese": "すきな",
      "english": "favorite",
      "type": "adjective",
      "exampleSentences": [
        {
          "japanese": "すきな食べ物は何ですか。",
          "english": "What is your favorite food?",
          "context": "question",
          "level": "1-1",
          "isAIGenerated": true
        },
        {
          "japanese": "私のすきないろはあおです。",
          "english": "My favorite color is blue.",
          "context": "statement",
          "level": "2-1",
          "isAIGenerated": true
        },
        {
          "japanese": "すきなアーティストのコンサートがありますから、来月東京に行きます。",
          "english": "There's a concert by my favorite artist, so I'm going to Tokyo next month.",
          "context": "statement",
          "level": "3-1",
          "isAIGenerated": true
        }
      ]
    },
    {
      "id": "duo_617",
      "japanese": "アトラクション",
      "english": "attraction",
      "type": "noun",
      "exampleSentences": [
        {
          "japanese": "このアトラクションはおもしろいです。",
          "english": "This attraction is fun.",
          "context": "statement",
          "level": "1-1",
          "isAIGenerated": true
        },
        {
          "japanese": "すきなアトラクションは何ですか。",
          "english": "What's your favorite attraction?",
          "context": "question",
          "level": "2-1",
          "isAIGenerated": true
        },
        {
          "japanese": "このゆうえんちにはアトラクションがたくさんありますが、ジェットコースターがいちばんにんきです。",
          "english": "This theme park has many attractions, but the rollercoaster is the most popular.",
          "context": "statement",
          "level": "3-1",
          "isAIGenerated": true
        }
      ]
    },
    {
      "id": "duo_616",
      "japanese": "こわい",
      "english": "scary",
      "type": "adjective",
      "exampleSentences": [
        {
          "japanese": "このえいがはこわいです。",
          "english": "This movie is scary.",
          "context": "statement",
          "level": "1-1",
          "isAIGenerated": true
        },
        {
          "japanese": "私はこわいえいがを見ません。",
          "english": "I don't watch scary movies.",
          "context": "statement",
          "level": "2-1",
          "isAIGenerated": true
        },
        {
          "japanese": "ジェットコースターはこわいですが、かのじょはだいすきです。",
          "english": "Rollercoasters are scary, but my girlfriend loves them.",
          "context": "statement",
          "level": "3-1",
          "isAIGenerated": true
        }
      ]
    },
    {
      "id": "duo_614",
      "japanese": "三千",
      "english": "3,000",
      "type": "noun",
      "exampleSentences": [
        {
          "japanese": "これは三千円です。",
          "english": "This is 3,000 yen.",
          "context": "statement",
          "level": "1-1",
          "isAIGenerated": true
        },
        {
          "japanese": "にゅうじょうりょうは三千円です。",
          "english": "The admission fee is 3,000 yen.",
          "context": "statement",
          "level": "2-1",
          "isAIGenerated": true
        },
        {
          "japanese": "このはくぶつかんのにゅうじょうりょうは三千円ですが、がくせいは千円です。",
          "english": "The admission fee for this museum is 3,000 yen, but it's 1,000 yen for students.",
          "context": "statement",
          "level": "3-1",
          "isAIGenerated": true
        }
      ]
    },
    {
      "id": "duo_608",
      "japanese": "ゆうえんち",
      "english": "theme park",
      "type": "noun",
      "exampleSentences": [
        {
          "japanese": "ゆうえんちに行きます。",
          "english": "I'm going to a theme park.",
          "context": "statement",
          "level": "1-1",
          "isAIGenerated": true
        },
        {
          "japanese": "こんしゅうまつ、かぞくとゆうえんちに行きませんか。",
          "english": "Would you like to go to a theme park with the family this weekend?",
          "context": "question",
          "level": "2-1",
          "isAIGenerated": true
        },
        {
          "japanese": "こどものたんじょうびに、ゆうえんちに行ってジェットコースターにのりたいです。",
          "english": "For my child's birthday, I want to go to a theme park and ride the rollercoaster.",
          "context": "statement",
          "level": "3-1",
          "isAIGenerated": true
        }
      ]
    },
    {
      "id": "duo_604",
      "japanese": "せんしゅ",
      "english": "athlete, athletes, player",
      "type": "noun",
      "exampleSentences": [
        {
          "japanese": "あのせんしゅはゆうめいです。",
          "english": "That athlete is famous.",
          "context": "statement",
          "level": "1-1",
          "isAIGenerated": true
        },
        {
          "japanese": "このサッカーせんしゅはとてもはやいです。",
          "english": "This soccer player is very fast.",
          "context": "statement",
          "level": "2-1",
          "isAIGenerated": true
        },
        {
          "japanese": "私のすきなやきゅうせんしゅは日本でとてもゆうめいですから、サインがほしいです。",
          "english": "My favorite baseball player is very famous in Japan, so I want their autograph.",
          "context": "statement",
          "level": "3-1",
          "isAIGenerated": true
        }
      ]
    },
    {
      "id": "duo_603",
      "japanese": "プロの",
      "english": "professional, pro",
      "type": "adjective",
      "exampleSentences": [
        {
          "japanese": "かれはプロのせんしゅです。",
          "english": "He is a professional athlete.",
          "context": "statement",
          "level": "1-1",
          "isAIGenerated": true
        },
        {
          "japanese": "あにはプロのしゃしんかです。",
          "english": "My older brother is a professional photographer.",
          "context": "statement",
          "level": "2-1",
          "isAIGenerated": true
        },
        {
          "japanese": "プロのサッカーせんしゅになりたいですから、まいにちれんしゅうしています。",
          "english": "I want to become a professional soccer player, so I practice every day.",
          "context": "statement",
          "level": "3-1",
          "isAIGenerated": true
        }
      ]
    },
    {
      "id": "duo_602",
      "japanese": "チーム",
      "english": "team",
      "type": "noun",
      "exampleSentences": [
        {
          "japanese": "私のチームはつよいです。",
          "english": "My team is strong.",
          "context": "statement",
          "level": "1-1",
          "isAIGenerated": true
        },
        {
          "japanese": "このチームには十人います。",
          "english": "There are ten people on this team.",
          "context": "statement",
          "level": "2-1",
          "isAIGenerated": true
        },
        {
          "japanese": "私のすきなやきゅうチームはきょねんしあいにかちましたから、とてもうれしかったです。",
          "english": "My favorite baseball team won the game last year, so I was very happy.",
          "context": "statement",
          "level": "3-1",
          "isAIGenerated": true
        }
      ]
    },
    {
      "id": "duo_596",
      "japanese": "ごぜん",
      "english": "a.m., morning",
      "type": "noun",
      "exampleSentences": [
        {
          "japanese": "ごぜん九時におきます。",
          "english": "I wake up at 9 a.m.",
          "context": "statement",
          "level": "1-1",
          "isAIGenerated": true
        },
        {
          "japanese": "ミーティングはごぜん十時からです。",
          "english": "The meeting is from 10 a.m.",
          "context": "statement",
          "level": "2-1",
          "isAIGenerated": true
        },
        {
          "japanese": "ごぜん六時におきて、シャワーをあびてから、あさごはんを食べます。",
          "english": "I wake up at 6 a.m., take a shower, and then eat breakfast.",
          "context": "statement",
          "level": "3-1",
          "isAIGenerated": true
        }
      ]
    },
    {
      "id": "duo_595",
      "japanese": "うんてんします",
      "english": "drive",
      "type": "verb",
      "exampleSentences": [
        {
          "japanese": "私は車をうんてんします。",
          "english": "I drive a car.",
          "context": "statement",
          "level": "1-1",
          "isAIGenerated": true
        },
        {
          "japanese": "父はまいにち車をうんてんしてしごとに行きます。",
          "english": "My father drives to work every day.",
          "context": "statement",
          "level": "2-1",
          "isAIGenerated": true
        },
        {
          "japanese": "来週、かぞくと車でほっかいどうまでうんてんしますから、ナビがひつようです。",
          "english": "Next week, I'll drive to Hokkaido with my family, so I need a GPS.",
          "context": "statement",
          "level": "3-1",
          "isAIGenerated": true
        }
      ]
    },
    {
      "id": "duo_594",
      "japanese": "ナビ",
      "english": "GPS",
      "type": "noun",
      "exampleSentences": [
        {
          "japanese": "ナビをつかいます。",
          "english": "I use GPS.",
          "context": "statement",
          "level": "1-1",
          "isAIGenerated": true
        },
        {
          "japanese": "車にナビがありますから、べんりです。",
          "english": "There's GPS in the car, so it's convenient.",
          "context": "statement",
          "level": "2-1",
          "isAIGenerated": true
        },
        {
          "japanese": "はじめてのところに行くとき、いつもナビをつかいますから、みちにまよいません。",
          "english": "When I go to a place for the first time, I always use GPS, so I don't get lost.",
          "context": "statement",
          "level": "3-1",
          "isAIGenerated": true
        }
      ]
    },
    {
      "id": "duo_591",
      "japanese": "ほんやくか",
      "english": "translator",
      "type": "noun",
      "exampleSentences": [
        {
          "japanese": "あねはほんやくかです。",
          "english": "My older sister is a translator.",
          "context": "statement",
          "level": "1-1",
          "isAIGenerated": true
        },
        {
          "japanese": "私はほんやくかになりたいです。",
          "english": "I want to become a translator.",
          "context": "statement",
          "level": "2-1",
          "isAIGenerated": true
        },
        {
          "japanese": "私のともだちはほんやくかで、えいごと日本ごとスペインごができます。",
          "english": "My friend is a translator and can speak English, Japanese, and Spanish.",
          "context": "statement",
          "level": "3-1",
          "isAIGenerated": true
        }
      ]
    },
    {
      "id": "duo_590",
      "japanese": "ほんやくします",
      "english": "translate",
      "type": "verb",
      "exampleSentences": [
        {
          "japanese": "日本ごをほんやくします。",
          "english": "I translate Japanese.",
          "context": "statement",
          "level": "1-1",
          "isAIGenerated": true
        },
        {
          "japanese": "このドキュメントをえいごにほんやくしてください。",
          "english": "Please translate this document into English.",
          "context": "statement",
          "level": "2-1",
          "isAIGenerated": true
        },
        {
          "japanese": "しごとで日本のしょうせつをえいごにほんやくしていますから、まいにちいそがしいです。",
          "english": "I translate Japanese novels into English for work, so I'm busy every day.",
          "context": "statement",
          "level": "3-1",
          "isAIGenerated": true
        }
      ]
    },
    {
      "id": "duo_588",
      "japanese": "じしょ",
      "english": "dictionary",
      "type": "noun",
      "exampleSentences": [
        {
          "japanese": "じしょをつかいます。",
          "english": "I use a dictionary.",
          "context": "statement",
          "level": "1-1",
          "isAIGenerated": true
        },
        {
          "japanese": "わからないことばはじしょで見ます。",
          "english": "I look up words I don't understand in the dictionary.",
          "context": "statement",
          "level": "2-1",
          "isAIGenerated": true
        },
        {
          "japanese": "日本ごをべんきょうするとき、いつもスマホのじしょをつかっています。",
          "english": "When I study Japanese, I always use a dictionary on my smartphone.",
          "context": "statement",
          "level": "3-1",
          "isAIGenerated": true
        }
      ]
    },
    {
      "id": "duo_585",
      "japanese": "かいしゃ",
      "english": "company",
      "type": "noun",
      "exampleSentences": [
        {
          "japanese": "私のかいしゃは東京にあります。",
          "english": "My company is in Tokyo.",
          "context": "statement",
          "level": "1-1",
          "isAIGenerated": true
        },
        {
          "japanese": "このかいしゃはとても大きいです。",
          "english": "This company is very big.",
          "context": "statement",
          "level": "2-1",
          "isAIGenerated": true
        },
        {
          "japanese": "大学をそつぎょうしてから、大きいかいしゃではたらきたいですが、まずえいごをべんきょうします。",
          "english": "After graduating from university, I want to work at a big company, but first I'll study English.",
          "context": "statement",
          "level": "3-1",
          "isAIGenerated": true
        }
      ]
    },
    {
      "id": "duo_580",
      "japanese": "プロジェクト",
      "english": "project",
      "type": "noun",
      "exampleSentences": [
        {
          "japanese": "新しいプロジェクトがあります。",
          "english": "I have a new project.",
          "context": "statement",
          "level": "1-1",
          "isAIGenerated": true
        },
        {
          "japanese": "このプロジェクトはたいへんですが、おもしろいです。",
          "english": "This project is tough, but interesting.",
          "context": "statement",
          "level": "2-1",
          "isAIGenerated": true
        },
        {
          "japanese": "来月、大きいプロジェクトがはじまりますから、チームでたくさんミーティングをしています。",
          "english": "A big project starts next month, so we're having many meetings as a team.",
          "context": "statement",
          "level": "3-1",
          "isAIGenerated": true
        }
      ]
    },
    {
      "id": "duo_579",
      "japanese": "しめきり",
      "english": "deadline",
      "type": "noun",
      "exampleSentences": [
        {
          "japanese": "しめきりはいつですか。",
          "english": "When is the deadline?",
          "context": "question",
          "level": "1-1",
          "isAIGenerated": true
        },
        {
          "japanese": "しめきりは来週の金曜日です。",
          "english": "The deadline is next Friday.",
          "context": "statement",
          "level": "2-1",
          "isAIGenerated": true
        },
        {
          "japanese": "しめきりがもうすぐですから、まいにちおそくまではたらいています。",
          "english": "The deadline is coming soon, so I'm working late every day.",
          "context": "statement",
          "level": "3-1",
          "isAIGenerated": true
        }
      ]
    },
    {
      "id": "duo_569",
      "japanese": "何曜日",
      "english": "what day",
      "type": "noun",
      "exampleSentences": [
        {
          "japanese": "今日は何曜日ですか。",
          "english": "What day is it today?",
          "context": "question",
          "level": "1-1",
          "isAIGenerated": true
        },
        {
          "japanese": "しあいは何曜日ですか。土曜日です。",
          "english": "What day is the game? It's Saturday.",
          "context": "answer",
          "level": "2-1",
          "isAIGenerated": true
        },
        {
          "japanese": "日本ごのじゅぎょうは何曜日にありますか。月曜日と水曜日にあります。",
          "english": "What days do you have Japanese class? I have it on Monday and Wednesday.",
          "context": "answer",
          "level": "3-1",
          "isAIGenerated": true
        }
      ]
    },
    {
      "id": "duo_567",
      "japanese": "スミス",
      "english": "Smith",
      "type": "noun",
      "exampleSentences": [
        {
          "japanese": "スミスさんはせんせいです。",
          "english": "Mr. Smith is a teacher.",
          "context": "statement",
          "level": "1-1",
          "isAIGenerated": true
        },
        {
          "japanese": "スミスさんはアメリカからきました。",
          "english": "Mr. Smith came from America.",
          "context": "statement",
          "level": "2-1",
          "isAIGenerated": true
        },
        {
          "japanese": "スミスさんは日本ごがじょうずですから、いつも日本ごで話します。",
          "english": "Mr. Smith is good at Japanese, so he always speaks in Japanese.",
          "context": "statement",
          "level": "3-1",
          "isAIGenerated": true
        }
      ]
    },
    {
      "id": "duo_566",
      "japanese": "山田",
      "english": "Yamada",
      "type": "noun",
      "exampleSentences": [
        {
          "japanese": "山田さんはがくせいです。",
          "english": "Mr. Yamada is a student.",
          "context": "statement",
          "level": "1-1",
          "isAIGenerated": true
        },
        {
          "japanese": "山田さんは私のどうりょうです。",
          "english": "Mr. Yamada is my coworker.",
          "context": "statement",
          "level": "2-1",
          "isAIGenerated": true
        },
        {
          "japanese": "山田さんはとてもしんせつですから、新しいしごとをよくおしえてくれます。",
          "english": "Mr. Yamada is very kind, so he often teaches me new work.",
          "context": "statement",
          "level": "3-1",
          "isAIGenerated": true
        }
      ]
    },
    {
      "id": "duo_563",
      "japanese": "スペインご",
      "english": "Spanish",
      "type": "noun",
      "exampleSentences": [
        {
          "japanese": "スペインごをべんきょうしています。",
          "english": "I'm studying Spanish.",
          "context": "statement",
          "level": "1-1",
          "isAIGenerated": true
        },
        {
          "japanese": "私はスペインごがすこしできます。",
          "english": "I can speak a little Spanish.",
          "context": "statement",
          "level": "2-1",
          "isAIGenerated": true
        },
        {
          "japanese": "来年スペインにりょこうしたいですから、今スペインごをべんきょうしています。",
          "english": "I want to travel to Spain next year, so I'm studying Spanish now.",
          "context": "statement",
          "level": "3-1",
          "isAIGenerated": true
        }
      ]
    },
    {
      "id": "duo_562",
      "japanese": "きょうしつ",
      "english": "classroom",
      "type": "noun",
      "exampleSentences": [
        {
          "japanese": "きょうしつはどこですか。",
          "english": "Where is the classroom?",
          "context": "question",
          "level": "1-1",
          "isAIGenerated": true
        },
        {
          "japanese": "日本ごのきょうしつは二階にあります。",
          "english": "The Japanese classroom is on the second floor.",
          "context": "statement",
          "level": "2-1",
          "isAIGenerated": true
        },
        {
          "japanese": "このきょうしつはひろくてあかるいですから、べんきょうしやすいです。",
          "english": "This classroom is spacious and bright, so it's easy to study.",
          "context": "statement",
          "level": "3-1",
          "isAIGenerated": true
        }
      ]
    },
    {
      "id": "duo_560",
      "japanese": "しょっぱい",
      "english": "salty",
      "type": "adjective",
      "exampleSentences": [
        {
          "japanese": "このスープはしょっぱいです。",
          "english": "This soup is salty.",
          "context": "statement",
          "level": "1-1",
          "isAIGenerated": true
        },
        {
          "japanese": "しょっぱい食べ物はあまりすきじゃないです。",
          "english": "I don't really like salty food.",
          "context": "statement",
          "level": "2-1",
          "isAIGenerated": true
        },
        {
          "japanese": "このラーメンはすこししょっぱいですから、水をたくさん飲みます。",
          "english": "This ramen is a bit salty, so I drink a lot of water.",
          "context": "statement",
          "level": "3-1",
          "isAIGenerated": true
        }
      ]
    },
    {
      "id": "duo_559",
      "japanese": "コーラ",
      "english": "cola",
      "type": "noun",
      "exampleSentences": [
        {
          "japanese": "コーラをください。",
          "english": "Cola, please.",
          "context": "statement",
          "level": "1-1",
          "isAIGenerated": true
        },
        {
          "japanese": "私はコーラがすきですが、あまり飲みません。",
          "english": "I like cola, but I don't drink it much.",
          "context": "statement",
          "level": "2-1",
          "isAIGenerated": true
        },
        {
          "japanese": "えいがかんでポップコーンとつめたいコーラを買いませんか。",
          "english": "Would you like to buy popcorn and cold cola at the movie theater?",
          "context": "question",
          "level": "3-1",
          "isAIGenerated": true
        }
      ]
    },
    {
      "id": "duo_558",
      "japanese": "飲みません",
      "english": "(I) won't drink, don't take, (I) do not drink",
      "type": "verb",
      "exampleSentences": [
        {
          "japanese": "私はコーヒーを飲みません。",
          "english": "I don't drink coffee.",
          "context": "statement",
          "level": "1-1",
          "isAIGenerated": true
        },
        {
          "japanese": "私はビールをあまり飲みません。",
          "english": "I don't drink beer much.",
          "context": "statement",
          "level": "2-1",
          "isAIGenerated": true
        },
        {
          "japanese": "明日うんてんしますから、今夜はおさけを飲みません。",
          "english": "I'm driving tomorrow, so I won't drink alcohol tonight.",
          "context": "statement",
          "level": "3-1",
          "isAIGenerated": true
        }
      ]
    },
    {
      "id": "duo_556",
      "japanese": "とんかつ",
      "english": "pork cutlet",
      "type": "noun",
      "exampleSentences": [
        {
          "japanese": "とんかつがすきです。",
          "english": "I like pork cutlet.",
          "context": "statement",
          "level": "1-1",
          "isAIGenerated": true
        },
        {
          "japanese": "ひるごはんにとんかつを食べませんか。",
          "english": "Would you like to eat pork cutlet for lunch?",
          "context": "question",
          "level": "2-1",
          "isAIGenerated": true
        },
        {
          "japanese": "日本のとんかつはとてもおいしいですから、ソースをつけて食べてください。",
          "english": "Japanese pork cutlet is very delicious, so please eat it with sauce.",
          "context": "statement",
          "level": "3-1",
          "isAIGenerated": true
        }
      ]
    },
    {
      "id": "duo_555",
      "japanese": "しお",
      "english": "salt",
      "type": "noun",
      "exampleSentences": [
        {
          "japanese": "しおをください。",
          "english": "Salt, please.",
          "context": "statement",
          "level": "1-1",
          "isAIGenerated": true
        },
        {
          "japanese": "りょうりにしおをいれてください。",
          "english": "Please put salt in the dish.",
          "context": "statement",
          "level": "2-1",
          "isAIGenerated": true
        },
        {
          "japanese": "私はステーキにしおとこしょうだけをつかいますが、ソースはつかいません。",
          "english": "I only use salt and pepper on steak, but I don't use sauce.",
          "context": "statement",
          "level": "3-1",
          "isAIGenerated": true
        }
      ]
    },
    {
      "id": "duo_554",
      "japanese": "ソース",
      "english": "sauce",
      "type": "noun",
      "exampleSentences": [
        {
          "japanese": "ソースをください。",
          "english": "Sauce, please.",
          "context": "statement",
          "level": "1-1",
          "isAIGenerated": true
        },
        {
          "japanese": "とんかつにソースをかけますか。",
          "english": "Do you put sauce on pork cutlet?",
          "context": "question",
          "level": "2-1",
          "isAIGenerated": true
        },
        {
          "japanese": "このソースはからいですが、とてもおいしいですから、ぜひつかってみてください。",
          "english": "This sauce is spicy, but it's very delicious, so please try using it.",
          "context": "statement",
          "level": "3-1",
          "isAIGenerated": true
        }
      ]
    },
    {
      "id": "duo_553",
      "japanese": "つかいましょう",
      "english": "we should use",
      "type": "verb",
      "exampleSentences": [
        {
          "japanese": "これをつかいましょう。",
          "english": "Let's use this.",
          "context": "statement",
          "level": "1-1",
          "isAIGenerated": true
        },
        {
          "japanese": "新しいパソコンをつかいましょう。",
          "english": "Let's use the new computer.",
          "context": "statement",
          "level": "2-1",
          "isAIGenerated": true
        },
        {
          "japanese": "時間がありませんから、タクシーをつかいましょう。",
          "english": "We don't have time, so let's use a taxi.",
          "context": "statement",
          "level": "3-1",
          "isAIGenerated": true
        }
      ]
    },
    {
      "id": "duo_552",
      "japanese": "なま",
      "english": "raw",
      "type": "noun",
      "exampleSentences": [
        {
          "japanese": "なまの魚を食べますか。",
          "english": "Do you eat raw fish?",
          "context": "question",
          "level": "1-1",
          "isAIGenerated": true
        },
        {
          "japanese": "すしはなまの魚をつかいます。",
          "english": "Sushi uses raw fish.",
          "context": "statement",
          "level": "2-1",
          "isAIGenerated": true
        },
        {
          "japanese": "日本りょうりにはなまの魚をつかうりょうりがおおいですから、新しいものがだいじです。",
          "english": "Japanese cuisine has many dishes using raw fish, so freshness is important.",
          "context": "statement",
          "level": "3-1",
          "isAIGenerated": true
        }
      ]
    },
    {
      "id": "duo_551",
      "japanese": "とうふ",
      "english": "(the) tofu, bean curd, tofu",
      "type": "noun",
      "exampleSentences": [
        {
          "japanese": "とうふがすきです。",
          "english": "I like tofu.",
          "context": "statement",
          "level": "1-1",
          "isAIGenerated": true
        },
        {
          "japanese": "みそしるにとうふをいれます。",
          "english": "I put tofu in miso soup.",
          "context": "statement",
          "level": "2-1",
          "isAIGenerated": true
        },
        {
          "japanese": "とうふは体にいいですから、私はまいにち食べています。",
          "english": "Tofu is good for the body, so I eat it every day.",
          "context": "statement",
          "level": "3-1",
          "isAIGenerated": true
        }
      ]
    }
  ]
}